pyensemblefs/__init__.py
pyensemblefs/api.py
pyensemblefs/cli.py
pyensemblefs/configs.py
pyensemblefs/main.py
pyensemblefs/main_stab.py
pyensemblefs/pipeline.py
pyensemblefs/aggregators/__init__.py
pyensemblefs/aggregators/abcvote.py
pyensemblefs/aggregators/base.py
pyensemblefs/aggregators/rank.py
pyensemblefs/aggregators/score.py
pyensemblefs/aggregators/subset.py
pyensemblefs/datasets/__init__.py
pyensemblefs/datasets/breast_cancer.py
pyensemblefs/datasets/cancer.py
pyensemblefs/datasets/diabetes_sklearn.py
pyensemblefs/datasets/heart.py
pyensemblefs/datasets/pima.py
pyensemblefs/ensemble/__init__.py
pyensemblefs/ensemble/base.py
pyensemblefs/ensemble/bootstrapper.py
pyensemblefs/ensemble/featureselector.py
pyensemblefs/ensemble/metabootstrapper.py
pyensemblefs/estimators/base.py
pyensemblefs/estimators/evaluator.py
pyensemblefs/fsmethods/__init__.py
pyensemblefs/fsmethods/basefs.py
pyensemblefs/fsmethods/factory.py
pyensemblefs/fsmethods/rank.py
pyensemblefs/fsmethods/score.py
pyensemblefs/fsmethods/subset.py
pyensemblefs/fsmethods/variance.py
pyensemblefs/selectors/__init__.py
pyensemblefs/selectors/base.py
pyensemblefs/selectors/filters.py
pyensemblefs/selectors/model_based.py
pyensemblefs/stability/__init__.py
pyensemblefs/stability/base.py
pyensemblefs/stability/config.py
pyensemblefs/stability/evaluator.py
pyensemblefs/stability/expectations.py
pyensemblefs/stability/frequency.py
pyensemblefs/stability/helpers.py
pyensemblefs/stability/measures_adjusted_intersections.py
pyensemblefs/stability/measures_adjusted_other.py
pyensemblefs/stability/measures_unadjusted.py
pyensemblefs/stability/pairwise.py
pyensemblefs/stability/stability.py
pyensemblefs/stability/utils_io.py
pyensemblefs/tools/generate_feature_sets.py
pyensemblefs/tools/sim_matrix.py
pyensemblefs/utils/consts.py
pyensemblefs/utils/datasets.py
pyensemblefs/utils/loader.py
pyensemblefs/utils/plotter.py
pyensemblefs/viz/__init__.py
pyensemblefs/viz/comparison.py
pyensemblefs/viz/ranking.py
pyensemblefs-0.3.13.dist-info/licenses/LICENSE
pyensemblefs-0.3.13.dist-info/METADATA
pyensemblefs-0.3.13.dist-info/WHEEL
pyensemblefs-0.3.13.dist-info/entry_points.txt
pyensemblefs-0.3.13.dist-info/top_level.txt
pyensemblefs-0.3.13.dist-info/RECORD
