Metadata-Version: 2.4
Name: pyensemblefs
Version: 0.3.13
Summary: Ensemble feature selection with bootstrapping, heterogeneous selectors, and stability analysis.
Author: David Chushig-Muzo, Bryan Peralta-Arboleda, Eva Milara, Cristina Soguero-Ruiz
License: MIT License
Project-URL: Homepage, https://github.com/cdchushig/pyensemblefs.git
Project-URL: Issues, https://github.com/cdchushig
Keywords: feature selection,ensemble,stability,machine learning
Classifier: Programming Language :: Python :: 3
Classifier: Programming Language :: Python :: 3 :: Only
Classifier: License :: OSI Approved :: MIT License
Classifier: Operating System :: OS Independent
Classifier: Topic :: Scientific/Engineering :: Artificial Intelligence
Requires-Python: >=3.9
License-File: LICENSE
Requires-Dist: numpy>=1.23
Requires-Dist: pandas>=2.0
Requires-Dist: scikit-learn>=1.3
Requires-Dist: scipy>=1.10
Requires-Dist: networkx>=3.0
Requires-Dist: matplotlib>=3.7
Requires-Dist: seaborn>=0.13
Requires-Dist: upsetplot>=0.8
Requires-Dist: requests>=2.31
Requires-Dist: abcvoting>=2.0
Requires-Dist: coloredlogs>=15.0
Requires-Dist: tqdm>=4.66
Requires-Dist: joblib>=1.3
Requires-Dist: skrebate>=0.62
Provides-Extra: viz
Requires-Dist: matplotlib>=3.7; extra == "viz"
Requires-Dist: seaborn>=0.13; extra == "viz"
Requires-Dist: upsetplot>=0.8; extra == "viz"
Provides-Extra: relief
Requires-Dist: skrebate>=0.62; extra == "relief"
Provides-Extra: dev
Requires-Dist: pytest>=7; extra == "dev"
Requires-Dist: ruff>=0.4; extra == "dev"
Requires-Dist: mypy>=1.8; extra == "dev"
Requires-Dist: build>=1.2.1; extra == "dev"
Requires-Dist: twine>=5; extra == "dev"
Dynamic: license-file
